README.rst
setup.py
redis_proxy/__init__.py
redis_proxy/main.py
redis_proxy/proxy.py
redis_proxy.egg-info/PKG-INFO
redis_proxy.egg-info/SOURCES.txt
redis_proxy.egg-info/dependency_links.txt
redis_proxy.egg-info/entry_points.txt
redis_proxy.egg-info/not-zip-safe
redis_proxy.egg-info/requires.txt
redis_proxy.egg-info/top_level.txt