Metadata-Version: 1.1
Name: redis-proxy
Version: 0.0.2
Summary: a redis proxy that will seperate read and write
Home-page: https://github.com/youngking/redis_proxy
Author: Young King
Author-email: yanckin@gmail.com
License: BSD
Keywords: redis proxy
Platform: UNKNOWN
Classifier: Programming Language :: Python
Classifier: Environment :: Console
Classifier: Topic :: System :: Networking
Classifier: Framework :: Twisted
Classifier: License :: OSI Approved :: BSD License
